{"results":[[1,"2220023","None","Eternal Rune Weapon",9341],[2,"2320023","None","Eternal Rune Weapon",9309],[3,"2120023","None","Eternal Rune Weapon",9287],[4,"2220023","None","Deep Cuts",9223],[5,"2320023","None","Deep Cuts",9198],[6,"2120023","None","Deep Cuts",9195],[7,"2220023","None","Bone Spike Graveyard",9170],[8,"2220023","None","Bones of the Damned",9167],[9,"2220023","None","Marrowblood",9164],[10,"2220023","None","None",9133],[11,"2320023","None","Bones of the Damned",9131],[12,"2120023","None","Bone Spike Graveyard",9128],[13,"2320023","None","Bone Spike Graveyard",9124],[14,"2120023","None","Marrowblood",9119],[15,"2120023","None","None",9112],[16,"2120023","None","Bones of the Damned",9111],[17,"2320023","None","Marrowblood",9109],[18,"2120023","None","Embrace of the Darkfallen",9109],[19,"2220023","None","Embrace of the Darkfallen",9098],[20,"2320023","None","None",9084],[21,"2320023","None","Embrace of the Darkfallen",9079],[22,"3220023","None","Eternal Rune Weapon",8839],[23,"3320023","None","Eternal Rune Weapon",8807],[24,"3120023","None","Eternal Rune Weapon",8792],[25,"3120023","None","Deep Cuts",8729],[26,"3220023","None","Deep Cuts",8724],[27,"3320023","None","Deep Cuts",8695],[28,"3220023","None","Bone Spike Graveyard",8667],[29,"3220023","None","Marrowblood",8648],[30,"3220023","None","Embrace of the Darkfallen",8641],[31,"3120023","None","Bones of the Damned",8633],[32,"3220023","None","Bones of the Damned",8630],[33,"3320023","None","Bones of the Damned",8629],[34,"3220023","None","None",8628],[35,"3120023","None","Bone Spike Graveyard",8619],[36,"3120023","None","Marrowblood",8617],[37,"3120023","None","Embrace of the Darkfallen",8613],[38,"3320023","None","Bone Spike Graveyard",8612],[39,"3320023","None","None",8597],[40,"1220023","None","Eternal Rune Weapon",8595],[41,"3120023","None","None",8582],[42,"3320023","None","Marrowblood",8576],[43,"3320023","None","Embrace of the Darkfallen",8575],[44,"2220033","None","Eternal Rune Weapon",8572],[45,"1320023","None","Eternal Rune Weapon",8508],[46,"2320033","None","Eternal Rune Weapon",8499],[47,"1120023","None","Eternal Rune Weapon",8499],[48,"2120033","None","Eternal Rune Weapon",8493],[49,"2220033","None","Deep Cuts",8465],[50,"1220023","None","Deep Cuts",8459],[51,"1120023","None","Deep Cuts",8429],[52,"2320033","None","Deep Cuts",8422],[53,"2120033","None","Deep Cuts",8410],[54,"1320023","None","Deep Cuts",8404],[55,"2220033","None","Bones of the Damned",8400],[56,"2220033","None","Marrowblood",8384],[57,"1220023","None","Bones of the Damned",8383],[58,"2220033","None","Embrace of the Darkfallen",8374],[59,"1220023","None","None",8372],[60,"2120033","None","Bone Spike Graveyard",8368],[61,"1220023","None","Marrowblood",8362],[62,"2220033","None","None",8356],[63,"1120023","None","Bones of the Damned",8353],[64,"2320033","None","Bones of the Damned",8352],[65,"1220023","None","Bone Spike Graveyard",8351],[66,"2320033","None","Bone Spike Graveyard",8351],[67,"1220023","None","Embrace of the Darkfallen",8344],[68,"2120033","None","Bones of the Damned",8342],[69,"1320023","None","Bones of the Damned",8340],[70,"1320023","None","Embrace of the Darkfallen",8339],[71,"2320033","None","None",8338],[72,"1320023","None","Bone Spike Graveyard",8338],[73,"1320023","None","Marrowblood",8334],[74,"1320023","None","None",8334],[75,"2220033","None","Bone Spike Graveyard",8330],[76,"1120023","None","Marrowblood",8326],[77,"2120033","None","None",8323],[78,"1120023","None","Bone Spike Graveyard",8320],[79,"2320033","None","Embrace of the Darkfallen",8319],[80,"1120023","None","Embrace of the Darkfallen",8318],[81,"2320033","None","Marrowblood",8316],[82,"1120023","None","None",8308],[83,"2120033","None","Marrowblood",8303],[84,"2120033","None","Embrace of the Darkfallen",8303],[85,"3220033","None","Eternal Rune Weapon",8082],[86,"3120033","None","Eternal Rune Weapon",8047],[87,"3320033","None","Eternal Rune Weapon",8036],[88,"3220033","None","Deep Cuts",7941],[89,"3120033","None","Deep Cuts",7934],[90,"3320033","None","Deep Cuts",7915],[91,"3220033","None","Bone Spike Graveyard",7895],[92,"3120033","None","Bones of the Damned",7871],[93,"3220033","None","Bones of the Damned",7868],[94,"3220033","None","Embrace of the Darkfallen",7862],[95,"3320033","None","Bones of the Damned",7851],[96,"3220033","None","None",7849],[97,"3120033","None","Bone Spike Graveyard",7848],[98,"3220033","None","Marrowblood",7844],[99,"3320033","None","Bone Spike Graveyard",7833],[100,"3320033","None","Marrowblood",7827],[101,"3320033","None","Embrace of the Darkfallen",7817],[102,"3120033","None","None",7814],[103,"3320033","None","None",7806],[104,"3120033","None","Marrowblood",7803],[105,"3120033","None","Embrace of the Darkfallen",7793],[106,"1320033","None","Eternal Rune Weapon",7781],[107,"1220033","None","Eternal Rune Weapon",7774],[108,"1120033","None","Eternal Rune Weapon",7729],[109,"1320033","None","Deep Cuts",7663],[110,"1220033","None","Deep Cuts",7647],[111,"1120033","None","Deep Cuts",7633],[112,"1220033","None","Bones of the Damned",7595],[113,"1220033","None","None",7591],[114,"1220033","None","Bone Spike Graveyard",7581],[115,"1220033","None","Marrowblood",7577],[116,"1320033","None","Embrace of the Darkfallen",7577],[117,"1320033","None","None",7573],[118,"1320033","None","Bones of the Damned",7568],[119,"1320033","None","Marrowblood",7565],[120,"1320033","None","Bone Spike Graveyard",7555],[121,"1120033","None","Bones of the Damned",7553],[122,"1220033","None","Embrace of the Darkfallen",7552],[123,"1120033","None","None",7536],[124,"1120033","None","Bone Spike Graveyard",7536],[125,"1120033","None","Marrowblood",7519],[126,"1120033","None","Embrace of the Darkfallen",7513]],"metas":{"build_date":"Aug 16 2018","build_time":"13:35:24","git_revision":"2cf3353760","options":{"debug":false,"max_time":300.0,"expected_iteration_time":360.0,"vary_combat_length":0.2,"iterations":217,"target_error":0.4,"threads":32,"seed":15070806120273245945,"single_actor_batch":false,"queue_lag":0.005,"queue_lag_stddev":0.001,"gcd_lag":0.15,"gcd_lag_stddev":0.037,"channel_lag":0.25,"channel_lag_stddev":0.062,"queue_gcd_reduction":0.1,"strict_gcd_queue":0,"confidence":0.95,"confidence_estimator":1.9599639854089754,"world_lag":0.1,"world_lag_stddev":0.01,"travel_variance":0.0,"default_skill":1.0,"reaction_time":0.5,"regen_periodicity":0.25,"ignite_sampling_delta":0.2,"fixed_time":true,"optimize_expressions":true,"optimal_raid":1,"log":0,"debug_each":0,"stat_cache":1,"max_aoe_enemies":20,"show_etmi":false,"tmi_window_global":0.0,"tmi_bin_size":0.5,"enemy_death_pct":0.0,"challenge_mode":false,"timewalk":-1,"pvp_crit":false,"rng":{"name":"sse2-sfmt"},"deterministic":0,"average_range":1,"average_gauss":0,"fight_style":"Patchwerk","default_aura_delay":0.03,"default_aura_delay_stddev":0.005,"dbc":{"bfa-BETA":{"build_level":26095,"wow_version":"8.0.1"},"version_used":"bfa-BETA"}},"overrides":{"arcane_intellect":1,"battle_shout":1,"power_word_fortitude":1,"chaos_brand":1,"mystic_touch":1,"mortal_wounds":1,"bleeding":1,"bloodlust":1,"bloodlust_percent":25,"bloodlust_time":0.5},"statistics":{"elapsed_cpu_seconds":1475.92282,"elapsed_time_seconds":1.890136,"init_time_seconds":1.5167809930000007,"merge_time_seconds":0.0075214340000000005,"analyze_time_seconds":0.02674442700000001,"simulation_length":{"sum":55651.89300000001,"count":185,"mean":300.8210432432433,"min":240.0,"max":360.0,"median":300.0,"variance":956.2540407116438,"std_dev":30.92335752649838,"mean_variance":5.16894076060348,"mean_std_dev":2.273530461771621},"raid_dps":{"sum":1588689.6526986277,"count":185,"mean":8587.511636208797},"raid_hps":{"sum":19217.84267926934,"count":185,"mean":103.88023069875318},"raid_aps":{"sum":4261.7050239643395,"count":185,"mean":23.036243372780213},"total_dmg":{"sum":477649724.4008447,"count":185,"mean":2581890.402166728},"total_heal":{"sum":5780751.719137429,"count":185,"mean":31247.30658993205},"total_absorb":{"sum":1282289.8639177096,"count":185,"mean":6931.296561717349},"total_iterations":14334,"total_actors":127,"total_iterations_mean":112.86614173228347,"total_iterations_variance":46722.72440944882,"total_iterations_stddev":216.15439946817835,"total_mean_dps_stddev":16.577015653750806,"total_mean_dps_variance":274.79744798469926},"player":{"name":"Template","race":"undead","level":120,"role":"tank","specialization":"Blood Death Knight","profile_source":"default","talents":[{"tier":1,"id":19217,"spell_id":210764,"name":"Rune Strike"},{"tier":2,"id":19219,"spell_id":273946,"name":"Hemostasis"},{"tier":3,"id":22134,"spell_id":219786,"name":"Ossuary"},{"tier":4,"id":22014,"spell_id":205727,"name":"Anti-Magic Barrier"},{"tier":6,"id":19231,"spell_id":195679,"name":"Bloodworms"},{"tier":7,"id":21208,"spell_id":205723,"name":"Red Thirst"}],"party":0,"ready_type":0,"bugs":true,"scale_player":true,"potion_used":false,"timeofday":"DAY_TIME","invert_scaling":0,"reaction_offset":0.1,"reaction_max":1.4000000000000001,"reaction_mean":0.3,"reaction_stddev":0.06,"reaction_nu":0.25,"world_lag":0.1,"brain_lag":0.0,"brain_lag_stddev":0.0,"world_lag_override":false,"world_lag_stddev_override":false,"dbc":{"bfa-BETA":{"build_level":26095,"wow_version":"8.0.1"},"version_used":"bfa-BETA"},"collected_data":{"fight_length":{"sum":55651.89299999999,"count":185,"mean":300.8210432432432,"min":240.0,"max":360.0},"waiting_time":{"sum":7419.700000000001,"count":185,"mean":40.10648648648649,"min":27.0,"max":53.0},"executed_foreground_actions":{"sum":45422.0,"count":185,"mean":245.5243243243243,"min":195.0,"max":295.0},"dmg":{"sum":422680270.91317225,"count":185,"mean":2284758.2211522823,"min":1762858.9501599232,"max":2863118.829727202},"compound_dmg":{"sum":477649724.4008447,"count":185,"mean":2581890.402166728,"min":2021755.228628274,"max":3185842.4011924397},"timeline_dmg":{"mean":9897.856379845434,"mean_std_dev":3070.5613318387755,"min":0.0,"max":31031.05327761312,"data":[7391.871403115047,9046.715088059254,21598.58110544837,8886.215200083892,31031.05327761312,15247.494514058873,14166.996329443085,17823.140031074843,15718.866288578945,4254.8287749293395,16280.173596159711,23252.460977782583,19682.88687324547,10705.190599340483,15659.500804435787,11459.93354603765,9401.595299774212,11449.87327555758,13740.559514020437,21715.449830375743,14818.265393147296,9977.779767859005,12077.280679052892,12121.588333962389,13851.20237417769,8287.912984496441,13302.254055153284,9415.26539204767,13570.481798708362,10523.191490531144,12868.091213860098,9784.633032724463,14072.719820473636,12169.489776797971,8977.442729860684,10802.55790243303,13040.229436954698,10298.304672705706,12001.800306788244,11618.399285291724,10995.211449379041,8392.182472660335,11426.939305170346,6616.175669848475,10350.298442314863,9601.99324800376,12101.107768683876,9640.874877232014,10285.276591943762,8556.574675199912,11607.735390969015,8198.494201981935,12423.54204620614,12250.623229730007,10995.352086426125,5403.045909213267,9820.874700430564,7938.6867720421515,8875.22339463321,13090.93019451763,8771.722985092396,10756.762830131616,8886.451365521636,5320.20228019933,8021.0413580501745,12334.248544798847,5954.7198846874735,9238.420714927643,14721.315017910541,7419.430687063726,10109.112236505123,8054.804785906146,7185.3170905917705,8333.264761208327,12491.497296019463,10671.89540711561,9471.944960132829,7442.626676556858,6586.588807065299,5941.943641810376,7752.176040085282,6840.367908197747,14195.100298687266,10321.605421908618,10497.239996046186,6039.827682665638,7172.905332253553,6708.217970160101,10710.095261661922,9391.176446996364,7404.492807688648,11869.500917955185,13974.913676393127,8884.841268162478,10030.634154474148,10069.757024212451,10105.974878958563,8063.523721461674,12712.55501994875,10787.55619241386,9660.22483679277,8350.95732299148,8482.787116619213,8374.18467948341,10556.366325978392,12091.10749583307,9072.63463456176,8419.710559659237,6764.852241714469,6098.783063432722,8905.91016391906,12951.138634489713,8269.446840552871,7203.475899372797,11363.407927642775,6277.712616469121,12100.953678267852,7399.808477624512,7759.413975861811,9792.04441809453,4056.241553951171,16186.995501417065,17106.11727904646,13887.755010613602,12873.825050008612,17655.095456405907,14108.681448399582,8671.926755994533,15017.200137601383,10200.166647162861,8901.28157147651,8578.259507264012,8038.797694943867,10608.379464888245,13454.541788395381,11199.175080422288,10145.643810473603,12310.078236482848,14872.516523591592,12722.754074353388,13357.414631108115,9061.37280886443,11204.61256452873,13710.811077919758,8776.437619356144,13077.798164210833,12019.040576859823,7078.378051359839,9224.043641959302,9376.699131030828,7290.929209242678,12320.427067260522,11088.23397190209,9136.385519540487,7289.913755304996,6952.457917684921,9154.454655388976,8562.35104043714,9423.71608057515,9881.70322076194,8165.046391071259,8061.815409272064,10541.6546025074,7071.7951092985495,9297.507630726184,8706.608561784726,10920.25306883008,11500.468628549137,10846.595435915924,6752.267994257719,7358.257513560572,7088.656679205619,8634.957768717759,6025.767964051496,12129.51693480019,8771.809617109999,13272.597619202472,5660.7692218408465,6419.1054553102185,10896.33521374327,9142.220866766394,9950.169598597246,12282.49340410764,9287.410030037525,10959.92059056986,11855.563168066381,9176.52914197454,9336.796494323988,10900.289645276938,10892.543693896465,11063.564437954668,9218.943202618553,8883.068766998576,6961.513499689573,10131.41690840989,9718.315491493426,6557.726427292329,13494.319271719141,8682.716192840857,7772.676261742848,7994.709678229994,6680.633567869149,9826.704702642335,11152.351930722567,7332.2025183512515,11310.786642640418,8872.56411777775,4792.511551867612,10815.852609382324,9665.15007464724,7331.242296531381,9131.715844242655,13123.28858031704,8335.27987873061,10395.482020036241,8005.0662964594585,6729.2814997317655,6599.958001538595,10756.866406590414,8830.497084612845,9209.559981128597,8898.157747087487,9339.675656814085,6750.524186012736,8996.928971693107,8743.61859918716,11510.27351365802,9760.048839394656,11443.554043200327,10633.258004017982,8955.653272060184,11164.98641738014,10080.143925674014,9666.449852812884,11686.095110389668,9505.40698279662,11321.469590730976,10823.708875267623,6575.036253330031,8352.02144737729,5439.826159505647,10398.781762346902,18740.669902590675,11585.103839281599,13483.608429420592,13853.545828709312,15319.515205028692,9522.328204377929,12658.55073752185,8068.871264810945,8644.835327646717,10982.26299664768,9386.956816740738,6176.471752133634,13732.037003636733,7697.734810186214,7012.529425532409,10861.62399068266,11127.023712212835,11026.478992892762,12328.645133803435,6528.721625081099,7318.542945850729,8126.821576803918,8264.61342642543,11865.169534503391,7496.022221398803,8253.122417082212,11131.145584378086,10869.12974132144,10822.11307358821,8400.296752898672,12227.168545446742,10582.58031463334,9169.321068243065,12759.703262149173,8365.18428982578,9627.06931885086,10637.541079941166,7365.415492122486,8982.167626197868,13267.985818855455,9431.656442151974,11829.32791637852,8548.415243317064,7011.984197327616,8841.149222856795,11103.597132448744,11724.64410741247,9393.2644918288,9577.06618883324,13754.321396388135,11245.400777176352,8812.868422372227,10535.40235146361,10830.407531023377,11355.187978496953,9501.69127052437,9003.959733339096,10753.09871184328,2791.5560116764145,8293.846699347145,10274.470500358912,5501.474373662573,9836.25009850801,7748.264408273493,8645.38578252325,4276.721580700239,6863.2263929440305,6747.496558572902,8528.136078306386,11515.394212615172,7579.765520008748,3374.8409828149656,11660.77685288442,6902.1154939854105,8085.073688863495,11322.662779007778,9449.039883704841,7456.907930542098,10176.385851361283,4475.425974730868,8610.768727089344,10612.578759200234,7321.634638817855,7920.729867218345,8821.6040259599,8872.945047060164,7234.951114608828,10946.604051786931,7535.9790523310185,6451.4236308433065,8255.12248622001,7937.2460932618105,10374.056521041253,12122.917967653344,6706.981454670566,7394.097399097331,5432.227849944931,5245.460104921566,7173.9290722926435,10790.320065814793,8409.149608113965,8147.356154597336,7921.00673610439,6175.281240884905,8944.949034000181,8503.573120028974,10494.982357241337,8812.780758242276,11260.209340525244,7773.8909431531,12239.138337842578,7834.50446910937,6231.433167825014,7169.665131618567,11427.00772595106,6763.213436839262,11476.364653344337,7038.743948070553,0.0]},"dps":{"sum":1588689.6526986274,"count":185,"mean":8587.511636208797,"min":7982.176948599762,"max":9106.901817512473,"median":8598.115994812215,"variance":41872.927835902556,"std_dev":204.6287561314454,"mean_variance":226.34015046433814,"mean_std_dev":15.044605360870658},"dpse":{"sum":1588689.6526986277,"count":185,"mean":8587.511636208797,"min":7982.176948599762,"max":9106.901817512473},"dtps":{"sum":5838003.68549066,"count":185,"mean":31556.776678327893,"min":25355.534659733185,"max":38192.69195137056},"timeline_dmg_taken":{"mean":120.03705518833246,"mean_std_dev":204.31226242723167,"min":0.0,"max":667.658903114187,"data":[0.0,0.0,0.0,0.0,25.617077250580355,648.2466162162162,23.35537124390889,649.6791606970542,43.52435670180793,470.77691160572334,47.03079961985667,470.77691160572334,23.05341404732568,470.77691160572334,0.0,470.77691160572334,0.0,470.77691160572334,0.0,470.77691160572334,0.0,470.77691160572334,0.0,470.77691160572334,0.0,0.0,0.0,0.0,0.0,0.0,0.0,0.0,0.0,0.0,0.0,0.0,0.0,0.0,0.0,0.0,0.0,0.0,175.1629837837838,0.0,0.0,0.0,470.77691160572334,0.0,470.77691160572334,0.0,471.90812334385237,0.0,470.77691160572334,0.0,470.77691160572334,0.0,470.77691160572334,0.0,470.77691160572334,0.0,470.77691160572334,0.0,470.77691160572334,0.0,470.77691160572334,0.0,0.5477537358581627,0.0,4.210528018672547,0.0,0.3081364796876248,0.0,0.0,0.0,1.6869894486893733,0.0,0.0,0.0,0.0,176.76765914149442,0.26574191145594034,0.0,1.431752339272821,0.0,0.0,0.0,0.0,470.77691160572334,1.6348711656621202,470.77691160572334,1.5923012634955716,470.77691160572334,0.582960907517128,470.77691160572334,0.0,470.77691160572334,0.864779675427961,470.77691160572334,0.0,470.77691160572334,0.0,470.77691160572334,0.0,470.77691160572334,0.0,470.77691160572334,0.0,0.0,0.0,0.0,1.4197851600226394,0.0,0.8107839951563893,0.0,7.88748403814098,0.0,176.16062734499206,0.0,0.0,0.0,3.6460982111128395,0.0,0.5753809496404751,0.0,0.0,0.0,0.0,0.0,470.77691160572334,0.0,470.77691160572334,0.0,470.77691160572334,0.0,471.0566839940806,0.0,475.1679342356427,0.0,472.3878394879496,0.0,470.77691160572334,0.0,471.62877609122,0.0,470.77691160572334,0.0,470.77691160572334,0.0,0.0,0.0,0.0,0.0,0.0,0.0,177.22161335453103,0.0,1.099745853248629,0.0,0.29557008519079075,0.0,0.8360720723124377,0.0,1.1687220799745948,0.0,0.5775819095930131,0.0,3.402648732165261,0.0,0.0,470.77691160572334,0.0,470.77691160572334,0.8867102555723723,470.77691160572334,0.8785752990992312,470.77691160572334,0.0,470.77691160572334,0.5152139099655986,470.77691160572334,5.178368198650152,483.89568747340434,3.0586993275097147,470.77691160572334,0.0,470.77691160572334,0.0,470.77691160572334,0.2820118244022224,0.0,0.0,177.03158600953896,0.0,0.0,0.0,0.0,0.0,0.0,0.0,0.0,0.0,0.0,1.9851424817102847,0.0,1.896696456404739,0.0,0.55317704017359,0.0,0.5924738432647821,0.0,471.88055403391274,0.0,474.1935933244426,0.0,470.77691160572334,0.0,470.77691160572334,0.0,471.3219536894237,0.0,470.77691160572334,0.0,470.77691160572334,0.0,471.3409352545278,0.0,475.02678305709435,0.0,650.989303248061,0.0,0.5721586052775858,0.0,0.0,0.0,0.5462470522560567,0.0,0.0,0.0,0.0,0.0,0.0,0.0,0.0,0.0,0.0,0.0,0.0,0.0,0.0,0.0,0.0,479.1918598930481,0.0,479.1918598930481,0.0,479.1918598930481,2.7492386959782054,479.1918598930481,5.017283225666837,479.6664835007174,0.0,478.6328505663135,1.3352272939136043,483.1581412514049,3.7006945378074754,667.658903114187,0.3147643288953915,485.29682237600923,2.69178362489906,485.29682237600923,1.6314072063743998,0.0,5.755431129982131,0.0,1.0545727043858357,0.0,0.0,0.0,0.0,0.0,0.0,0.0,0.0,0.0,0.0,0.0,0.0,0.0,0.0,0.0,0.0,0.0,485.29682237600923,0.0,485.97553296018987,0.0,485.9640303908218,5.057149825037715,485.6443746558312,0.0,147.03052242283053,0.0,554.0821360593782,0.0,401.3535882352941,0.0,401.3535882352941,0.0,401.3535882352941,0.0,404.1258200397591,0.0,1.4018821823626175,0.0,0.0,0.0,0.0,0.0,0.0,0.0,0.0,0.0,0.0,0.0,0.0,0.0,0.0,0.0,0.0,0.0,0.0,0.0,0.0,401.3535882352941,0.0,401.3535882352941,0.0,401.3535882352941,0.0,548.8983048128342,1.5049669475310907,401.3535882352941,0.0,401.3535882352941,2.543348721231189,379.05616666666674,0.0,401.3535882352942,0.0,401.3535882352942,0.0,401.3535882352942,0.0,0.0,0.0,0.0,0.0,0.0,0.0,0.0,0.0]},"deaths":{"sum":0.0,"count":0,"mean":0.0,"min":0.0,"max":0.0},"theck_meloree_index":{"sum":9879871.646531962,"count":185,"mean":53404.71160287547,"min":52202.8027907535,"max":54196.11440589923,"median":53433.92972381638,"variance":141760.26628246522,"std_dev":376.5106456429422,"mean_variance":766.2717096349471,"mean_std_dev":27.681613205067134},"effective_theck_meloree_index":{"sum":11303503.52302897,"count":185,"mean":61100.019043399836,"min":61077.35850845564,"max":61118.31633174468},"max_spike_amount":{"sum":2.203309000260023,"count":5,"mean":0.4406618000520046,"min":0.39685588816937567,"max":0.5161082169803279},"heal":{"sum":5780751.719137429,"count":185,"mean":31247.30658993205,"min":25355.5346597319,"max":38192.691951368644},"compound_heal":{"sum":5780751.719137429,"count":185,"mean":31247.30658993205,"min":25355.5346597319,"max":38192.691951368644},"hps":{"sum":19217.842679269343,"count":185,"mean":103.88023069875321,"min":99.34739653938568,"max":107.45470120529978,"median":104.09706974753354,"variance":2.655267166919744,"std_dev":1.6294990539793952,"mean_variance":0.01435279549686348,"mean_std_dev":0.11980315311736783},"hpse":{"sum":19217.84267926934,"count":185,"mean":103.88023069875318,"min":99.34739653938568,"max":107.45470120529978},"absorb":{"sum":36246.67297263032,"count":5,"mean":7249.3345945260635,"min":5673.92691613453,"max":8711.941930414161},"compound_absorb":{"sum":36246.67297263032,"count":5,"mean":7249.3345945260635,"min":5673.92691613453,"max":8711.941930414161},"aps":{"sum":119.02110603868796,"count":5,"mean":23.80422120773759,"min":21.51202974011787,"max":25.837031676493893,"median":24.310311425906917,"variance":2.3024756876392987,"std_dev":1.5173910793329777,"mean_variance":0.46049513752785975,"mean_std_dev":0.6785979203680629},"htps":{"sum":19217.84267926934,"count":185,"mean":103.88023069875318,"min":99.34739653938568,"max":107.45470120529978},"heal_taken":{"sum":5780751.719137429,"count":185,"mean":31247.30658993205,"min":25355.5346597319,"max":38192.691951368644},"timeline_healing_taken":{"mean":-120.53252764324579,"mean_std_dev":148.2517288313278,"min":-991.924733250058,"max":0.0,"data":[0.0,0.0,0.0,0.0,-3.1866828594174286,-49.71666298015987,-22.40086274617918,-92.16568878275135,-152.88285499537344,-35.92972310988069,-234.28341006801898,-991.924733250058,-484.93382136991653,-458.2964735799208,-13.016873131954815,-110.64342162161593,-52.06749252781926,-338.43870143082523,-173.5583084260642,-911.1811192368372,-10.847394276629013,-210.43944896660287,-141.01612559617718,-349.28609570745425,-164.880393004761,-21.694788553258025,-30.372703974561237,-101.96550620031273,-47.728534817167656,-4.338957710651606,-19.525309697932222,0.0,0.0,0.0,0.0,0.0,0.0,0.0,0.0,0.0,0.0,0.0,-47.63352114467322,-4.133094753577324,-34.716940222574536,-33.80903179650195,-134.49185341811784,-77.88481875993249,-73.33999809220629,-70.44735961843854,-297.0724088764287,-129.54058537360226,-587.9287697932925,-338.43870143082523,-184.40570270269322,-21.694788553258025,-273.3543357710511,-112.81290047694173,-262.5069414944221,-442.5736864864637,-143.18560445150297,-321.0828705882188,-167.0498718600868,-117.15185818759335,-186.57518155801904,-138.84664674085138,-34.985538553141964,-152.1373967407353,-389.76592274531407,-80.88255916840642,-13.32500961164258,-2.169478855325803,0.0,-6.508436565977408,-10.3649048699925,0.0,0.0,0.0,0.0,-27.992083624801662,-14.473749443561129,-17.584622992536783,-58.88863151256322,-14.753511923688427,-26.18682384737547,-10.541239109697337,-1.573004133545328,-70.18871128775487,-48.89409608649392,-142.8525766689837,-132.59039382554144,-448.25276180994354,-306.47947950845526,-162.7109141494352,-80.2707176470547,-97.62654848966112,-256.8632846038729,-277.69329348170277,-433.89577106516055,-429.5568133545089,-82.4401965023805,-91.11811192368371,-119.32133704291914,-288.5406877583317,-275.5238146263769,-546.7086715421023,-52.06749252781926,-101.96550620031273,-34.711661685212846,-47.728534817167656,-28.203225119235434,-96.87685479435793,-4.338957710651606,-13.016873131954815,-51.240347289396574,-7.355934416394794,-33.8882098569154,-32.996137042925696,-10.388161526231812,-29.290603815580127,-4.101423529411566,-53.759931021668265,-14.416306803631596,-1.5413329093798844,0.0,0.0,0.0,0.0,-160.5414352941094,-80.2707176470547,-82.4401965023805,-80.2707176470547,-132.33821017487395,-195.25309697932224,-245.43088304017311,-188.74466041334483,-243.81837163709915,-145.89001262712486,-653.3044590936564,-336.2692225754994,-169.21935071541262,-56.40645023847087,-215.3399413257768,-343.06798897845124,-234.3037163751867,-340.608180286151,-134.50768903019977,-58.575929093796674,-145.3550833068288,-167.0498718600868,-52.06749252781926,-158.3719564387836,-10.847394276629013,-75.9317599364031,-35.08115930047572,-25.289472496025326,-19.667830206677507,-27.39741898520214,-4.877368521462887,-40.486353551008975,-22.76027325134806,-6.7593708400419485,-4.510036229418049,-0.8128947535772002,0.0,-2.235042640912611,-3.1233485599205753,-0.2793001722443748,0.0,-41.22009825119025,-32.54218282988704,-114.98237933226754,-189.63137066891713,-65.08436565977408,-380.53737498111457,-151.8635198728062,-420.87889793320574,-138.84664674085138,-132.33821017487395,-188.74466041334483,-202.38516085612764,-262.20738118075406,-318.50256322698317,-403.7860973498976,-325.4218282988704,-331.9302648648478,-106.30446391096433,-156.20247758345778,-221.5688550676342,-297.21860317963495,-182.23622384736743,-62.191727186007284,-23.230842925278104,-24.170422575515822,-45.53794181239949,-43.47403370429183,-14.30483624801304,-19.456688712241217,-1.5043831478536909,-7.168253736089085,-3.2463004769474217,0.0,0.0,-1.9851424817105983,-0.26031860714035765,-1.6363778492643473,-0.5531770401738105,0.0,-0.5924738432648844,0.0,-26.03374626390963,-123.66029475357075,-319.0947581691504,-210.43944896660287,-112.81290047694173,-75.9317599364031,-127.99925246422235,-147.52456216215458,-321.6279126719191,-425.2178556438573,-104.13498505563852,-36.881140540538645,-414.3704613672283,-193.08361812399644,-184.40570270269322,-225.62580095388347,-259.1042965321437,-231.4152552060292,-482.99881036200253,-407.0755227344806,-143.46536693163122,-113.77039230956439,-38.12159682034854,-45.92855357710442,-93.26903433365074,-25.912339904609237,-9.073805723370153,0.0,0.0,0.0,0.0,0.0,0.0,0.0,0.0,0.0,0.0,0.0,0.0,0.0,0.0,-107.02762352940627,-116.75740748662501,-138.6494213903672,-92.43294759357813,-148.37920534758595,-51.38235916490455,-299.20665600164403,-417.27630754781563,-502.9564425309335,-152.66210104654576,-104.7009360613757,-130.20343637888732,-148.62862133983245,-236.49566149766432,-507.50950633565094,-98.55489966145441,-116.71760361398886,-503.58116386324514,-278.2151441753034,-146.6769145762299,-162.7654987816091,-175.86869470226415,-181.8138948283166,-103.96034855982083,-104.30355324874536,-2.6232260668972125,0.0,0.0,0.0,0.0,0.0,0.0,0.0,0.0,0.0,0.0,0.0,0.0,0.0,0.0,0.0,-207.23485928487978,-78.69678200691637,-136.72579860264318,-170.8703618085113,-70.82710380622473,-271.99173501157964,-263.9718406213291,-333.14971049594595,-19.868989516597697,-249.4900683624673,-336.87032365872574,-102.66755166930946,-312.72694594593173,-295.91480445149637,-112.64398728139271,-69.35998092209479,-43.38957710651605,-134.4707392686742,-474.858220675666,-448.80763910967556,-70.60350698363224,0.0,-292.87964546898337,0.0,0.0,-10.847394276629013,0.0,0.0,0.0,0.0,0.0,0.0,0.0,0.0,0.0,0.0,0.0,0.0,0.0,0.0,0.0,-151.8635198728062,-151.8635198728062,-206.10049125595125,-65.08436565977408,-100.33839705881837,-47.21806920414982,-192.34670231728037,-148.76815257352428,-387.5948235675421,-216.89415756301398,-335.6006078431189,-246.35019185847514,-133.78452941175783,-125.42299632352297,-175.59219485293215,-250.84599264704593,-301.0151911764551,-150.50759558822756,-100.33839705881837,-326.0997904411597,-25.084599264704593,-114.67245378150672,0.0,-109.46006951871095,0.0,0.0,0.0,0.0]},"atps":{"sum":119.02110603868796,"count":5,"mean":23.80422120773759,"min":21.51202974011787,"max":25.837031676493893},"absorb_taken":{"sum":36246.67297263032,"count":5,"mean":7249.3345945260635,"min":5673.92691613453,"max":8711.941930414161},"target_metric":{"sum":1322001.0873028992,"count":185,"mean":8584.42264482402,"min":7982.176948599762,"max":9106.901817512473,"median":0.0,"variance":41078.357714209655,"std_dev":202.677965536981,"mean_variance":266.74258255980294,"mean_std_dev":16.33225589316439},"buffed_stats":{"attribute":{"strength":5842.0,"agility":1526.0,"stamina":15170.0,"intellect":1677.0},"resources":{"health":303400.0,"runic_power":125.0,"rune":6.0},"stats":{"attack_power":7562.35216,"spell_crit":0.17083333333333334,"attack_crit":0.17083333333333334,"spell_haste":0.8412718050228876,"attack_haste":0.8412718050228876,"spell_speed":0.8412718050228876,"attack_speed":0.8412718050228876,"mastery_value":0.3536,"damage_versatility":0.046941176470588236,"heal_versatility":0.046941176470588236,"mitigation_versatility":0.023470588235294118,"crit_rating":870.0,"crit_pct":0.17083333333333334,"haste_rating":1213.0,"haste_pct":0.18867647058823533,"mastery_rating":697.0,"mastery_pct":0.3536,"versatility_rating":399.0,"versatility_pct":0.046941176470588236,"speed_pct":7.0,"armor":4663.25,"dodge":0.06,"parry":0.22433746034221425}}},"gear":{"head":{"name":"gridrunner_galea","encoded_item":"gridrunner_galea,id=160634,bonus_id=4824/1507/4775,azerite_powers=13/481/21/15","ilevel":390,"strint":655,"stamina":1189},"neck":{"name":"heart_of_azeroth","encoded_item":"heart_of_azeroth,id=158075,bonus_id=4929/4930/4936/1536","ilevel":389,"haste_rating":251,"crit_rating":251,"mastery_rating":251,"stamina":326,"stragiint":192},"shoulders":{"name":"chitinspine_pauldrons","encoded_item":"chitinspine_pauldrons,id=160641,bonus_id=4824/1507/4775,azerite_powers=13/483/30/201","ilevel":390,"strint":491,"stamina":892},"chest":{"name":"chestguard_of_virulent_mutagens","encoded_item":"chestguard_of_virulent_mutagens,id=160636,bonus_id=4824/1507/4775,azerite_powers=13/483/459/15","ilevel":390,"strint":655,"stamina":1189},"waist":{"name":"decontaminators_greatbelt","encoded_item":"decontaminators_greatbelt,id=160638,bonus_id=4800/1507","ilevel":385,"strint":247,"stamina":417,"mastery_rating":123,"crit_rating":60},"legs":{"name":"greaves_of_unending_vigil","encoded_item":"greaves_of_unending_vigil,id=160639,bonus_id=4800/1507","ilevel":385,"strint":329,"stamina":556,"haste_rating":165,"mastery_rating":81},"feet":{"name":"warboots_of_absolute_eradication","encoded_item":"warboots_of_absolute_eradication,id=160640,bonus_id=4800/1507","ilevel":385,"strint":247,"stamina":417,"haste_rating":111,"versatility_rating":72},"wrists":{"name":"imperious_vambraces","encoded_item":"imperious_vambraces,id=160723,bonus_id=4800/1507","ilevel":385,"strint":185,"stamina":312,"versatility_rating":83,"haste_rating":54},"hands":{"name":"waste_disposal_crushers","encoded_item":"waste_disposal_crushers,id=160635,bonus_id=4800/1507","ilevel":385,"strint":247,"stamina":417,"crit_rating":115,"versatility_rating":68},"finger1":{"name":"band_of_certain_annihilation","encoded_item":"band_of_certain_annihilation,id=160646,bonus_id=4800/1507,enchant=pact_of_haste","ilevel":385,"stamina":312,"haste_rating":234,"mastery_rating":197},"finger2":{"name":"rotscour_ring","encoded_item":"rotscour_ring,id=160645,bonus_id=4800/1507,enchant=pact_of_haste","ilevel":385,"stamina":312,"crit_rating":302,"haste_rating":129},"trinket1":{"name":"syringe_of_bloodborne_infirmity","encoded_item":"syringe_of_bloodborne_infirmity,id=160655,bonus_id=4800/1507","ilevel":385,"strength":313},"trinket2":{"name":"vanquished_tendril_of_ghuun","encoded_item":"vanquished_tendril_of_ghuun,id=160654,bonus_id=4800/1507","ilevel":385,"versatility_rating":176},"back":{"name":"fetid_horrors_tanglecloak","encoded_item":"fetid_horrors_tanglecloak,id=160643,bonus_id=4800/1507","ilevel":385,"stragiint":185,"stamina":312,"haste_rating":92,"mastery_rating":45},"main_hand":{"name":"khor_hammer_of_the_corrupted","encoded_item":"khor_hammer_of_the_corrupted,id=160679,bonus_id=4800/1507,enchant=rune_of_the_fallen_crusader","ilevel":385,"strength":329,"stamina":556,"crit_rating":142,"haste_rating":103}},"custom":{}},"profilesets_overrides":{},"build_timestamp":1534419324,"result_timestamp":1534420992}}