{"data":{"site":{"siteMetadata":{"reportsPath":"/reports/"}},"relatedSimulationTypes":{"edges":[{"node":{"path":"/zh/priest/azeritelevels/2t-pr-shadow","context":{"simulationType":"azeritelevels"}}},{"node":{"path":"/zh/priest/azeritestacks/2t-pr-shadow","context":{"simulationType":"azeritestacks"}}},{"node":{"path":"/zh/priest/combinations/2t-pr-shadow","context":{"simulationType":"combinations"}}},{"node":{"path":"/zh/priest/trinkets/2t-pr-shadow","context":{"simulationType":"trinkets"}}},{"node":{"path":"/zh/priest/races/2t-pr-shadow","context":{"simulationType":"races"}}}]},"relatedTiers":{"edges":[{"node":{"path":"/zh/priest/combinations/2t-pr-shadow","context":{"tier":"pr"}}},{"node":{"path":"/zh/priest/combinations/2t-t22-shadow","context":{"tier":"t22"}}}]},"relatedSpecs":{"edges":[{"node":{"path":"/zh/priest/combinations/2t-pr-shadow","context":{"spec":"shadow","variation":""}}}]},"relatedFightStyles":{"edges":[{"node":{"path":"/zh/priest/combinations/1t-pr-shadow","context":{"fightStyle":"1t"}}},{"node":{"path":"/zh/priest/combinations/1ta-pr-shadow","context":{"fightStyle":"1ta"}}},{"node":{"path":"/zh/priest/combinations/2t-pr-shadow","context":{"fightStyle":"2t"}}},{"node":{"path":"/zh/priest/combinations/3t-pr-shadow","context":{"fightStyle":"3t"}}}]}},"pageContext":{"slug":"/priest/combinations/2t-pr-shadow","name":"Combinator_2T_PR_Priest_Shadow","wowClass":"priest","simulationType":"combinations","order":3,"template":"combinations","tier":"pr","fightStyle":"2t","spec":"shadow","variation":"","targetError":0.4,"resultTime":1535379105,"version":"8.0.1","build":27404,"buildTime":1535370642,"gitRevision":"4aa7462e31","templateDPS":12169,"lang":"zh"}}